dist
docs
netbox_cesnet_services_plugin
tests
