Metadata-Version: 2.4
Name: netbox_cesnet_services_plugin
Version: 2.0.0
Summary: NetBox plugin for CESNET services.
Author-email: Jan Krupa <jan.krupa@cesnet.cz>, Jiri Vrany <jiri.vrany@cesnet.cz>
License: MIT License
Project-URL: repository, https://gitlab.cesnet.cz/701/netbox/netbox_cesnet_services_plugin
Keywords: netbox,netbox-plugin,cesnet-services
Classifier: Development Status :: 5 - Production/Stable
Requires-Python: >=3.12
License-File: LICENSE
Requires-Dist: geocoder
Requires-Dist: python-slugify
Requires-Dist: deepdiff
Requires-Dist: netutils
Requires-Dist: netbox-scripts-lib
Dynamic: license-file
